[{"frame_idx":422,"tick":422,"port_idx":7,"vessel_idx":6,"action_scope":"ActionScope(load=962, discharge=19)","early_discharge":0,"attention_port":[0,3],"line_list":[[{"lat":45.516136,"lng":-73.65683},{"lat":53.549999,"lng":8.583333}],[{"lat":45.516136,"lng":-73.65683},{"lat":49.490002,"lng":0.1}]]},{"frame_idx":422,"tick":422,"port_idx":10,"vessel_idx":16,"action_scope":"ActionScope(load=313, discharge=10)","early_discharge":0,"attention_port":[16,9,4],"line_list":[[{"lat":54.312519,"lng":-130.305405},{"lat":31.224361,"lng":121.46917}],[{"lat":54.312519,"lng":-130.305405},{"lat":37.804363,"lng":-122.271111}],[{"lat":54.312519,"lng":-130.305405},{"lat":34.052235,"lng":-118.243683}]]},{"frame_idx":422,"tick":422,"port_idx":14,"vessel_idx":34,"action_scope":"ActionScope(load=631, discharge=6)","early_discharge":0,"attention_port":[16,2,20],"line_list":[[{"lat":-23.96083,"lng":-46.33361},{"lat":31.224361,"lng":121.46917}],[{"lat":-23.96083,"lng":-46.33361},{"lat":-22.85222,"lng":-43.77528}],[{"lat":-23.96083,"lng":-46.33361},{"lat":26.8533,"lng":119.8575}]]}]