[{"frame_index":97,"name":"ports_0","capacity":10000,"empty":4940,"full":2171,"on_shipper":120,"on_consignee":0,"shortage":0,"acc_shortage":0,"booking":101,"acc_booking":13226,"fulfillment":101,"acc_fulfillment":13226,"transfer_cost":0.0,"port_name":"Bremerhaven","position":{"lat":53.549999,"lng":8.583333},"status":"surplus"},{"frame_index":97,"name":"ports_1","capacity":10000,"empty":618,"full":79,"on_shipper":10,"on_consignee":0,"shortage":0,"acc_shortage":0,"booking":8,"acc_booking":887,"fulfillment":8,"acc_fulfillment":887,"transfer_cost":0.0,"port_name":"Durban","position":{"lat":-29.8579,"lng":31.0292},"status":"surplus"},{"frame_index":97,"name":"ports_2","capacity":10000,"empty":203,"full":508,"on_shipper":9,"on_consignee":0,"shortage":0,"acc_shortage":0,"booking":8,"acc_booking":877,"fulfillment":8,"acc_fulfillment":877,"transfer_cost":0.0,"port_name":"Itagual","position":{"lat":-22.85222,"lng":-43.77528},"status":"surplus"},{"frame_index":97,"name":"ports_3","capacity":10000,"empty":1785,"full":1019,"on_shipper":55,"on_consignee":0,"shortage":0,"acc_shortage":0,"booking":40,"acc_booking":5048,"fulfillment":40,"acc_fulfillment":5048,"transfer_cost":0.0,"port_name":"LeHavre","position":{"lat":49.490002,"lng":0.1},"status":"surplus"},{"frame_index":97,"name":"ports_4","capacity":10000,"empty":1840,"full":820,"on_shipper":43,"on_consignee":0,"shortage":0,"acc_shortage":0,"booking":34,"acc_booking":4210,"fulfillment":34,"acc_fulfillment":4210,"transfer_cost":0.0,"port_name":"Los Angeles","position":{"lat":34.052235,"lng":-118.243683},"status":"surplus"},{"frame_index":97,"name":"ports_5","capacity":10000,"empty":1115,"full":128,"on_shipper":36,"on_consignee":0,"shortage":0,"acc_shortage":0,"booking":29,"acc_booking":4177,"fulfillment":29,"acc_fulfillment":4177,"transfer_cost":0.0,"port_name":"Manzanillo","position":{"lat":19.11695,"lng":-104.34214},"status":"surplus"},{"frame_index":97,"name":"ports_6","capacity":10000,"empty":379,"full":327,"on_shipper":17,"on_consignee":0,"shortage":0,"acc_shortage":0,"booking":11,"acc_booking":1297,"fulfillment":11,"acc_fulfillment":1297,"transfer_cost":0.0,"port_name":"Melbourne","position":{"lat":-37.840935,"lng":144.946457},"status":"surplus"},{"frame_index":97,"name":"ports_7","capacity":10000,"empty":1567,"full":153,"on_shipper":17,"on_consignee":0,"shortage":0,"acc_shortage":0,"booking":11,"acc_booking":1292,"fulfillment":11,"acc_fulfillment":1292,"transfer_cost":0.0,"port_name":"Montreal","position":{"lat":45.516136,"lng":-73.65683},"status":"surplus"},{"frame_index":97,"name":"ports_8","capacity":10000,"empty":1422,"full":1418,"on_shipper":30,"on_consignee":0,"shortage":0,"acc_shortage":0,"booking":19,"acc_booking":2539,"fulfillment":19,"acc_fulfillment":2539,"transfer_cost":0.0,"port_name":"New York","position":{"lat":40.73061,"lng":-73.935242},"status":"surplus"},{"frame_index":97,"name":"ports_9","capacity":10000,"empty":1632,"full":35,"on_shipper":32,"on_consignee":0,"shortage":0,"acc_shortage":0,"booking":21,"acc_booking":2511,"fulfillment":21,"acc_fulfillment":2511,"transfer_cost":0.0,"port_name":"Oakland","position":{"lat":37.804363,"lng":-122.271111},"status":"surplus"},{"frame_index":97,"name":"ports_10","capacity":10000,"empty":551,"full":135,"on_shipper":13,"on_consignee":0,"shortage":0,"acc_shortage":0,"booking":11,"acc_booking":1290,"fulfillment":11,"acc_fulfillment":1290,"transfer_cost":0.0,"port_name":"Prince Rupert","position":{"lat":54.312519,"lng":-130.305405},"status":"surplus"},{"frame_index":97,"name":"ports_11","capacity":10000,"empty":1279,"full":1349,"on_shipper":47,"on_consignee":0,"shortage":0,"acc_shortage":0,"booking":42,"acc_booking":5035,"fulfillment":42,"acc_fulfillment":5035,"transfer_cost":0.0,"port_name":"Pusan","position":{"lat":35.166668,"lng":129.066666},"status":"surplus"},{"frame_index":97,"name":"ports_12","capacity":10000,"empty":2156,"full":2686,"on_shipper":75,"on_consignee":0,"shortage":0,"acc_shortage":0,"booking":59,"acc_booking":6706,"fulfillment":59,"acc_fulfillment":6706,"transfer_cost":0.0,"port_name":"Qingdao","position":{"lat":36.066898,"lng":120.382698},"status":"surplus"},{"frame_index":97,"name":"ports_13","capacity":10000,"empty":264,"full":188,"on_shipper":9,"on_consignee":0,"shortage":0,"acc_shortage":0,"booking":7,"acc_booking":885,"fulfillment":7,"acc_fulfillment":885,"transfer_cost":0.0,"port_name":"San Antonio","position":{"lat":29.424349,"lng":-98.491142},"status":"surplus"},{"frame_index":97,"name":"ports_14","capacity":10000,"empty":200,"full":6,"on_shipper":10,"on_consignee":0,"shortage":0,"acc_shortage":0,"booking":8,"acc_booking":886,"fulfillment":8,"acc_fulfillment":886,"transfer_cost":0.0,"port_name":"Santos","position":{"lat":-23.96083,"lng":-46.33361},"status":"surplus"},{"frame_index":97,"name":"ports_15","capacity":10000,"empty":1936,"full":2654,"on_shipper":68,"on_consignee":0,"shortage":0,"acc_shortage":0,"booking":49,"acc_booking":5886,"fulfillment":49,"acc_fulfillment":5886,"transfer_cost":0.0,"port_name":"Seattle","position":{"lat":47.608013,"lng":-122.335167},"status":"surplus"},{"frame_index":97,"name":"ports_16","capacity":10000,"empty":2162,"full":546,"on_shipper":73,"on_consignee":300,"shortage":0,"acc_shortage":0,"booking":56,"acc_booking":8411,"fulfillment":56,"acc_fulfillment":8411,"transfer_cost":0.0,"port_name":"Shanghai","position":{"lat":31.224361,"lng":121.46917},"status":"surplus"},{"frame_index":97,"name":"ports_17","capacity":10000,"empty":1806,"full":281,"on_shipper":30,"on_consignee":80,"shortage":0,"acc_shortage":0,"booking":27,"acc_booking":3382,"fulfillment":27,"acc_fulfillment":3382,"transfer_cost":0.0,"port_name":"Singapore","position":{"lat":1.29027,"lng":103.851959},"status":"surplus"},{"frame_index":97,"name":"ports_18","capacity":10000,"empty":369,"full":409,"on_shipper":12,"on_consignee":0,"shortage":0,"acc_shortage":0,"booking":11,"acc_booking":1275,"fulfillment":11,"acc_fulfillment":1275,"transfer_cost":0.0,"port_name":"Sydney","position":{"lat":-33.865143,"lng":151.2099},"status":"surplus"},{"frame_index":97,"name":"ports_19","capacity":10000,"empty":580,"full":259,"on_shipper":18,"on_consignee":213,"shortage":0,"acc_shortage":0,"booking":15,"acc_booking":1724,"fulfillment":15,"acc_fulfillment":1724,"transfer_cost":0.0,"port_name":"Vancouver","position":{"lat":49.246292,"lng":-123.116226},"status":"surplus"},{"frame_index":97,"name":"ports_20","capacity":10000,"empty":1936,"full":2022,"on_shipper":49,"on_consignee":0,"shortage":0,"acc_shortage":0,"booking":44,"acc_booking":5752,"fulfillment":44,"acc_fulfillment":5752,"transfer_cost":0.0,"port_name":"Yantian","position":{"lat":26.8533,"lng":119.8575},"status":"surplus"},{"frame_index":97,"name":"ports_21","capacity":10000,"empty":2653,"full":1072,"on_shipper":52,"on_consignee":0,"shortage":0,"acc_shortage":0,"booking":44,"acc_booking":5629,"fulfillment":44,"acc_fulfillment":5629,"transfer_cost":0.0,"port_name":"Yokohama","position":{"lat":35.443707,"lng":139.638031},"status":"surplus"}]