[{"frame_index":1023,"name":"ports_0","capacity":10000,"empty":4898,"full":83,"on_shipper":200,"on_consignee":466,"shortage":0,"acc_shortage":861,"booking":110,"acc_booking":130444,"fulfillment":110,"acc_fulfillment":129583,"transfer_cost":1150.0,"port_name":"Bremerhaven","position":{"lat":53.549999,"lng":8.583333},"status":"surplus"},{"frame_index":1023,"name":"ports_1","capacity":10000,"empty":276,"full":149,"on_shipper":11,"on_consignee":0,"shortage":0,"acc_shortage":113,"booking":6,"acc_booking":8676,"fulfillment":6,"acc_fulfillment":8563,"transfer_cost":0.0,"port_name":"Durban","position":{"lat":-29.8579,"lng":31.0292},"status":"surplus"},{"frame_index":1023,"name":"ports_2","capacity":10000,"empty":268,"full":357,"on_shipper":11,"on_consignee":0,"shortage":0,"acc_shortage":298,"booking":7,"acc_booking":8644,"fulfillment":7,"acc_fulfillment":8346,"transfer_cost":0.0,"port_name":"Itagual","position":{"lat":-22.85222,"lng":-43.77528},"status":"surplus"},{"frame_index":1023,"name":"ports_3","capacity":10000,"empty":6566,"full":207,"on_shipper":52,"on_consignee":0,"shortage":0,"acc_shortage":0,"booking":39,"acc_booking":49381,"fulfillment":39,"acc_fulfillment":49381,"transfer_cost":0.0,"port_name":"LeHavre","position":{"lat":49.490002,"lng":0.1},"status":"surplus"},{"frame_index":1023,"name":"ports_4","capacity":10000,"empty":2628,"full":138,"on_shipper":47,"on_consignee":216,"shortage":0,"acc_shortage":290,"booking":32,"acc_booking":41355,"fulfillment":32,"acc_fulfillment":41065,"transfer_cost":0.0,"port_name":"Los Angeles","position":{"lat":34.052235,"lng":-118.243683},"status":"surplus"},{"frame_index":1023,"name":"ports_5","capacity":10000,"empty":1763,"full":56,"on_shipper":64,"on_consignee":0,"shortage":0,"acc_shortage":194,"booking":35,"acc_booking":41379,"fulfillment":35,"acc_fulfillment":41185,"transfer_cost":0.0,"port_name":"Manzanillo","position":{"lat":19.11695,"lng":-104.34214},"status":"surplus"},{"frame_index":1023,"name":"ports_6","capacity":10000,"empty":370,"full":104,"on_shipper":16,"on_consignee":0,"shortage":0,"acc_shortage":2108,"booking":10,"acc_booking":12736,"fulfillment":10,"acc_fulfillment":10628,"transfer_cost":0.0,"port_name":"Melbourne","position":{"lat":-37.840935,"lng":144.946457},"status":"surplus"},{"frame_index":1023,"name":"ports_7","capacity":10000,"empty":1388,"full":120,"on_shipper":15,"on_consignee":0,"shortage":0,"acc_shortage":0,"booking":10,"acc_booking":12743,"fulfillment":10,"acc_fulfillment":12743,"transfer_cost":0.0,"port_name":"Montreal","position":{"lat":45.516136,"lng":-73.65683},"status":"surplus"},{"frame_index":1023,"name":"ports_8","capacity":10000,"empty":3263,"full":206,"on_shipper":28,"on_consignee":0,"shortage":0,"acc_shortage":136,"booking":18,"acc_booking":24896,"fulfillment":18,"acc_fulfillment":24760,"transfer_cost":0.0,"port_name":"New York","position":{"lat":40.73061,"lng":-73.935242},"status":"surplus"},{"frame_index":1023,"name":"ports_9","capacity":10000,"empty":1790,"full":24,"on_shipper":32,"on_consignee":0,"shortage":0,"acc_shortage":45,"booking":22,"acc_booking":24932,"fulfillment":22,"acc_fulfillment":24887,"transfer_cost":0.0,"port_name":"Oakland","position":{"lat":37.804363,"lng":-122.271111},"status":"surplus"},{"frame_index":1023,"name":"ports_10","capacity":10000,"empty":1577,"full":29,"on_shipper":17,"on_consignee":0,"shortage":0,"acc_shortage":314,"booking":11,"acc_booking":12748,"fulfillment":11,"acc_fulfillment":12434,"transfer_cost":0.0,"port_name":"Prince Rupert","position":{"lat":54.312519,"lng":-130.305405},"status":"surplus"},{"frame_index":1023,"name":"ports_11","capacity":10000,"empty":2852,"full":953,"on_shipper":58,"on_consignee":0,"shortage":0,"acc_shortage":204,"booking":38,"acc_booking":49328,"fulfillment":38,"acc_fulfillment":49124,"transfer_cost":0.0,"port_name":"Pusan","position":{"lat":35.166668,"lng":129.066666},"status":"surplus"},{"frame_index":1023,"name":"ports_12","capacity":10000,"empty":4373,"full":1600,"on_shipper":97,"on_consignee":0,"shortage":0,"acc_shortage":0,"booking":50,"acc_booking":65963,"fulfillment":50,"acc_fulfillment":65963,"transfer_cost":0.0,"port_name":"Qingdao","position":{"lat":36.066898,"lng":120.382698},"status":"surplus"},{"frame_index":1023,"name":"ports_13","capacity":10000,"empty":283,"full":70,"on_shipper":11,"on_consignee":0,"shortage":0,"acc_shortage":459,"booking":7,"acc_booking":8649,"fulfillment":7,"acc_fulfillment":8190,"transfer_cost":0.0,"port_name":"San Antonio","position":{"lat":29.424349,"lng":-98.491142},"status":"surplus"},{"frame_index":1023,"name":"ports_14","capacity":10000,"empty":45,"full":190,"on_shipper":12,"on_consignee":0,"shortage":0,"acc_shortage":876,"booking":6,"acc_booking":8697,"fulfillment":6,"acc_fulfillment":7821,"transfer_cost":0.0,"port_name":"Santos","position":{"lat":-23.96083,"lng":-46.33361},"status":"balance"},{"frame_index":1023,"name":"ports_15","capacity":10000,"empty":1917,"full":803,"on_shipper":72,"on_consignee":0,"shortage":0,"acc_shortage":1489,"booking":42,"acc_booking":57587,"fulfillment":42,"acc_fulfillment":56098,"transfer_cost":0.0,"port_name":"Seattle","position":{"lat":47.608013,"lng":-122.335167},"status":"surplus"},{"frame_index":1023,"name":"ports_16","capacity":10000,"empty":2982,"full":962,"on_shipper":80,"on_consignee":0,"shortage":0,"acc_shortage":817,"booking":63,"acc_booking":82175,"fulfillment":63,"acc_fulfillment":81358,"transfer_cost":0.0,"port_name":"Shanghai","position":{"lat":31.224361,"lng":121.46917},"status":"surplus"},{"frame_index":1023,"name":"ports_17","capacity":10000,"empty":605,"full":575,"on_shipper":31,"on_consignee":0,"shortage":0,"acc_shortage":619,"booking":25,"acc_booking":33165,"fulfillment":25,"acc_fulfillment":32546,"transfer_cost":0.0,"port_name":"Singapore","position":{"lat":1.29027,"lng":103.851959},"status":"surplus"},{"frame_index":1023,"name":"ports_18","capacity":10000,"empty":792,"full":0,"on_shipper":20,"on_consignee":172,"shortage":0,"acc_shortage":1374,"booking":9,"acc_booking":12745,"fulfillment":9,"acc_fulfillment":11371,"transfer_cost":0.0,"port_name":"Sydney","position":{"lat":-33.865143,"lng":151.2099},"status":"surplus"},{"frame_index":1023,"name":"ports_19","capacity":10000,"empty":1417,"full":0,"on_shipper":16,"on_consignee":282,"shortage":0,"acc_shortage":0,"booking":12,"acc_booking":16860,"fulfillment":12,"acc_fulfillment":16860,"transfer_cost":0.0,"port_name":"Vancouver","position":{"lat":49.246292,"lng":-123.116226},"status":"surplus"},{"frame_index":1023,"name":"ports_20","capacity":10000,"empty":1126,"full":617,"on_shipper":60,"on_consignee":0,"shortage":0,"acc_shortage":1425,"booking":46,"acc_booking":57301,"fulfillment":46,"acc_fulfillment":55876,"transfer_cost":0.0,"port_name":"Yantian","position":{"lat":26.8533,"lng":119.8575},"status":"surplus"},{"frame_index":1023,"name":"ports_21","capacity":10000,"empty":918,"full":110,"on_shipper":67,"on_consignee":0,"shortage":0,"acc_shortage":7747,"booking":38,"acc_booking":54484,"fulfillment":38,"acc_fulfillment":46737,"transfer_cost":0.0,"port_name":"Yokohama","position":{"lat":35.443707,"lng":139.638031},"status":"surplus"}]