[{"frame_index":145,"name":"ports_0","capacity":10000,"empty":6350,"full":2180,"on_shipper":221,"on_consignee":0,"shortage":0,"acc_shortage":0,"booking":128,"acc_booking":17215,"fulfillment":128,"acc_fulfillment":17215,"transfer_cost":0.0,"port_name":"Bremerhaven","position":{"lat":53.549999,"lng":8.583333},"status":"surplus"},{"frame_index":145,"name":"ports_1","capacity":10000,"empty":710,"full":150,"on_shipper":20,"on_consignee":0,"shortage":0,"acc_shortage":0,"booking":8,"acc_booking":1161,"fulfillment":8,"acc_fulfillment":1161,"transfer_cost":0.0,"port_name":"Durban","position":{"lat":-29.8579,"lng":31.0292},"status":"surplus"},{"frame_index":145,"name":"ports_2","capacity":10000,"empty":0,"full":720,"on_shipper":0,"on_consignee":0,"shortage":9,"acc_shortage":74,"booking":9,"acc_booking":1154,"fulfillment":0,"acc_fulfillment":1080,"transfer_cost":0.0,"port_name":"Itagual","position":{"lat":-22.85222,"lng":-43.77528},"status":"balance"},{"frame_index":145,"name":"ports_3","capacity":10000,"empty":1871,"full":764,"on_shipper":99,"on_consignee":0,"shortage":0,"acc_shortage":0,"booking":46,"acc_booking":6577,"fulfillment":46,"acc_fulfillment":6577,"transfer_cost":0.0,"port_name":"LeHavre","position":{"lat":49.490002,"lng":0.1},"status":"surplus"},{"frame_index":145,"name":"ports_4","capacity":10000,"empty":2654,"full":972,"on_shipper":76,"on_consignee":0,"shortage":0,"acc_shortage":0,"booking":39,"acc_booking":5494,"fulfillment":39,"acc_fulfillment":5494,"transfer_cost":0.0,"port_name":"Los Angeles","position":{"lat":34.052235,"lng":-118.243683},"status":"surplus"},{"frame_index":145,"name":"ports_5","capacity":10000,"empty":551,"full":113,"on_shipper":76,"on_consignee":0,"shortage":0,"acc_shortage":0,"booking":41,"acc_booking":5430,"fulfillment":41,"acc_fulfillment":5430,"transfer_cost":0.0,"port_name":"Manzanillo","position":{"lat":19.11695,"lng":-104.34214},"status":"surplus"},{"frame_index":145,"name":"ports_6","capacity":10000,"empty":701,"full":139,"on_shipper":19,"on_consignee":0,"shortage":0,"acc_shortage":0,"booking":12,"acc_booking":1695,"fulfillment":12,"acc_fulfillment":1695,"transfer_cost":0.0,"port_name":"Melbourne","position":{"lat":-37.840935,"lng":144.946457},"status":"surplus"},{"frame_index":145,"name":"ports_7","capacity":10000,"empty":2633,"full":70,"on_shipper":12,"on_consignee":0,"shortage":0,"acc_shortage":0,"booking":12,"acc_booking":1690,"fulfillment":12,"acc_fulfillment":1690,"transfer_cost":0.0,"port_name":"Montreal","position":{"lat":45.516136,"lng":-73.65683},"status":"surplus"},{"frame_index":145,"name":"ports_8","capacity":10000,"empty":1256,"full":575,"on_shipper":54,"on_consignee":0,"shortage":0,"acc_shortage":0,"booking":22,"acc_booking":3313,"fulfillment":22,"acc_fulfillment":3313,"transfer_cost":0.0,"port_name":"New York","position":{"lat":40.73061,"lng":-73.935242},"status":"surplus"},{"frame_index":145,"name":"ports_9","capacity":10000,"empty":1953,"full":420,"on_shipper":43,"on_consignee":0,"shortage":0,"acc_shortage":0,"booking":21,"acc_booking":3285,"fulfillment":21,"acc_fulfillment":3285,"transfer_cost":0.0,"port_name":"Oakland","position":{"lat":37.804363,"lng":-122.271111},"status":"surplus"},{"frame_index":145,"name":"ports_10","capacity":10000,"empty":177,"full":0,"on_shipper":18,"on_consignee":960,"shortage":0,"acc_shortage":0,"booking":10,"acc_booking":1686,"fulfillment":10,"acc_fulfillment":1686,"transfer_cost":22.0,"port_name":"Prince Rupert","position":{"lat":54.312519,"lng":-130.305405},"status":"surplus"},{"frame_index":145,"name":"ports_11","capacity":10000,"empty":2343,"full":446,"on_shipper":71,"on_consignee":137,"shortage":0,"acc_shortage":0,"booking":47,"acc_booking":6544,"fulfillment":47,"acc_fulfillment":6544,"transfer_cost":0.0,"port_name":"Pusan","position":{"lat":35.166668,"lng":129.066666},"status":"surplus"},{"frame_index":145,"name":"ports_12","capacity":10000,"empty":3751,"full":878,"on_shipper":78,"on_consignee":465,"shortage":0,"acc_shortage":0,"booking":56,"acc_booking":8736,"fulfillment":56,"acc_fulfillment":8736,"transfer_cost":455.0,"port_name":"Qingdao","position":{"lat":36.066898,"lng":120.382698},"status":"surplus"},{"frame_index":145,"name":"ports_13","capacity":10000,"empty":242,"full":222,"on_shipper":21,"on_consignee":0,"shortage":0,"acc_shortage":0,"booking":8,"acc_booking":1162,"fulfillment":8,"acc_fulfillment":1162,"transfer_cost":0.0,"port_name":"San Antonio","position":{"lat":29.424349,"lng":-98.491142},"status":"surplus"},{"frame_index":145,"name":"ports_14","capacity":10000,"empty":11,"full":206,"on_shipper":7,"on_consignee":0,"shortage":0,"acc_shortage":0,"booking":7,"acc_booking":1165,"fulfillment":7,"acc_fulfillment":1165,"transfer_cost":0.0,"port_name":"Santos","position":{"lat":-23.96083,"lng":-46.33361},"status":"balance"},{"frame_index":145,"name":"ports_15","capacity":10000,"empty":2764,"full":259,"on_shipper":99,"on_consignee":997,"shortage":0,"acc_shortage":0,"booking":53,"acc_booking":7645,"fulfillment":53,"acc_fulfillment":7645,"transfer_cost":0.0,"port_name":"Seattle","position":{"lat":47.608013,"lng":-122.335167},"status":"surplus"},{"frame_index":145,"name":"ports_16","capacity":10000,"empty":2543,"full":801,"on_shipper":164,"on_consignee":0,"shortage":0,"acc_shortage":0,"booking":79,"acc_booking":10968,"fulfillment":79,"acc_fulfillment":10968,"transfer_cost":0.0,"port_name":"Shanghai","position":{"lat":31.224361,"lng":121.46917},"status":"surplus"},{"frame_index":145,"name":"ports_17","capacity":10000,"empty":1011,"full":518,"on_shipper":50,"on_consignee":515,"shortage":0,"acc_shortage":0,"booking":31,"acc_booking":4416,"fulfillment":31,"acc_fulfillment":4416,"transfer_cost":0.0,"port_name":"Singapore","position":{"lat":1.29027,"lng":103.851959},"status":"surplus"},{"frame_index":145,"name":"ports_18","capacity":10000,"empty":551,"full":258,"on_shipper":13,"on_consignee":0,"shortage":0,"acc_shortage":0,"booking":13,"acc_booking":1673,"fulfillment":13,"acc_fulfillment":1673,"transfer_cost":0.0,"port_name":"Sydney","position":{"lat":-33.865143,"lng":151.2099},"status":"surplus"},{"frame_index":145,"name":"ports_19","capacity":10000,"empty":497,"full":533,"on_shipper":40,"on_consignee":0,"shortage":0,"acc_shortage":0,"booking":15,"acc_booking":2247,"fulfillment":15,"acc_fulfillment":2247,"transfer_cost":0.0,"port_name":"Vancouver","position":{"lat":49.246292,"lng":-123.116226},"status":"surplus"},{"frame_index":145,"name":"ports_20","capacity":10000,"empty":2151,"full":565,"on_shipper":101,"on_consignee":95,"shortage":0,"acc_shortage":0,"booking":54,"acc_booking":7505,"fulfillment":54,"acc_fulfillment":7505,"transfer_cost":0.0,"port_name":"Yantian","position":{"lat":26.8533,"lng":119.8575},"status":"surplus"},{"frame_index":145,"name":"ports_21","capacity":10000,"empty":3544,"full":229,"on_shipper":108,"on_consignee":0,"shortage":0,"acc_shortage":0,"booking":49,"acc_booking":7117,"fulfillment":49,"acc_fulfillment":7117,"transfer_cost":0.0,"port_name":"Yokohama","position":{"lat":35.443707,"lng":139.638031},"status":"surplus"}]