[{"frame_index":112,"name":"ports_0","capacity":10000,"empty":4918,"full":2490,"on_shipper":122,"on_consignee":567,"shortage":0,"acc_shortage":0,"booking":77,"acc_booking":14132,"fulfillment":77,"acc_fulfillment":14132,"transfer_cost":4.0,"port_name":"Bremerhaven","position":{"lat":53.549999,"lng":8.583333},"status":"surplus"},{"frame_index":112,"name":"ports_1","capacity":10000,"empty":554,"full":145,"on_shipper":8,"on_consignee":0,"shortage":0,"acc_shortage":0,"booking":6,"acc_booking":951,"fulfillment":6,"acc_fulfillment":951,"transfer_cost":0.0,"port_name":"Durban","position":{"lat":-29.8579,"lng":31.0292},"status":"surplus"},{"frame_index":112,"name":"ports_2","capacity":10000,"empty":143,"full":572,"on_shipper":5,"on_consignee":0,"shortage":0,"acc_shortage":0,"booking":5,"acc_booking":937,"fulfillment":5,"acc_fulfillment":937,"transfer_cost":0.0,"port_name":"Itagual","position":{"lat":-22.85222,"lng":-43.77528},"status":"surplus"},{"frame_index":112,"name":"ports_3","capacity":10000,"empty":1645,"full":1049,"on_shipper":42,"on_consignee":420,"shortage":0,"acc_shortage":0,"booking":31,"acc_booking":5384,"fulfillment":31,"acc_fulfillment":5384,"transfer_cost":274.0,"port_name":"LeHavre","position":{"lat":49.490002,"lng":0.1},"status":"surplus"},{"frame_index":112,"name":"ports_4","capacity":10000,"empty":2474,"full":14,"on_shipper":34,"on_consignee":1180,"shortage":0,"acc_shortage":0,"booking":25,"acc_booking":4494,"fulfillment":25,"acc_fulfillment":4494,"transfer_cost":0.0,"port_name":"Los Angeles","position":{"lat":34.052235,"lng":-118.243683},"status":"surplus"},{"frame_index":112,"name":"ports_5","capacity":10000,"empty":843,"full":411,"on_shipper":25,"on_consignee":0,"shortage":0,"acc_shortage":0,"booking":25,"acc_booking":4449,"fulfillment":25,"acc_fulfillment":4449,"transfer_cost":0.0,"port_name":"Manzanillo","position":{"lat":19.11695,"lng":-104.34214},"status":"surplus"},{"frame_index":112,"name":"ports_6","capacity":10000,"empty":594,"full":153,"on_shipper":9,"on_consignee":0,"shortage":0,"acc_shortage":0,"booking":8,"acc_booking":1388,"fulfillment":8,"acc_fulfillment":1388,"transfer_cost":0.0,"port_name":"Melbourne","position":{"lat":-37.840935,"lng":144.946457},"status":"surplus"},{"frame_index":112,"name":"ports_7","capacity":10000,"empty":1477,"full":249,"on_shipper":11,"on_consignee":0,"shortage":0,"acc_shortage":0,"booking":8,"acc_booking":1382,"fulfillment":8,"acc_fulfillment":1382,"transfer_cost":0.0,"port_name":"Montreal","position":{"lat":45.516136,"lng":-73.65683},"status":"surplus"},{"frame_index":112,"name":"ports_8","capacity":10000,"empty":1854,"full":3,"on_shipper":28,"on_consignee":0,"shortage":0,"acc_shortage":0,"booking":16,"acc_booking":2715,"fulfillment":16,"acc_fulfillment":2715,"transfer_cost":0.0,"port_name":"New York","position":{"lat":40.73061,"lng":-73.935242},"status":"surplus"},{"frame_index":112,"name":"ports_9","capacity":10000,"empty":1456,"full":222,"on_shipper":21,"on_consignee":0,"shortage":0,"acc_shortage":0,"booking":17,"acc_booking":2687,"fulfillment":17,"acc_fulfillment":2687,"transfer_cost":0.0,"port_name":"Oakland","position":{"lat":37.804363,"lng":-122.271111},"status":"surplus"},{"frame_index":112,"name":"ports_10","capacity":10000,"empty":460,"full":227,"on_shipper":12,"on_consignee":0,"shortage":0,"acc_shortage":0,"booking":8,"acc_booking":1381,"fulfillment":8,"acc_fulfillment":1381,"transfer_cost":0.0,"port_name":"Prince Rupert","position":{"lat":54.312519,"lng":-130.305405},"status":"surplus"},{"frame_index":112,"name":"ports_11","capacity":10000,"empty":1682,"full":854,"on_shipper":36,"on_consignee":0,"shortage":0,"acc_shortage":0,"booking":30,"acc_booking":5367,"fulfillment":30,"acc_fulfillment":5367,"transfer_cost":0.0,"port_name":"Pusan","position":{"lat":35.166668,"lng":129.066666},"status":"surplus"},{"frame_index":112,"name":"ports_12","capacity":10000,"empty":3258,"full":1158,"on_shipper":47,"on_consignee":0,"shortage":0,"acc_shortage":0,"booking":36,"acc_booking":7139,"fulfillment":36,"acc_fulfillment":7139,"transfer_cost":0.0,"port_name":"Qingdao","position":{"lat":36.066898,"lng":120.382698},"status":"surplus"},{"frame_index":112,"name":"ports_13","capacity":10000,"empty":459,"full":19,"on_shipper":7,"on_consignee":0,"shortage":0,"acc_shortage":0,"booking":5,"acc_booking":945,"fulfillment":5,"acc_fulfillment":945,"transfer_cost":0.0,"port_name":"San Antonio","position":{"lat":29.424349,"lng":-98.491142},"status":"surplus"},{"frame_index":112,"name":"ports_14","capacity":10000,"empty":135,"full":76,"on_shipper":5,"on_consignee":0,"shortage":0,"acc_shortage":0,"booking":5,"acc_booking":951,"fulfillment":5,"acc_fulfillment":951,"transfer_cost":0.0,"port_name":"Santos","position":{"lat":-23.96083,"lng":-46.33361},"status":"surplus"},{"frame_index":112,"name":"ports_15","capacity":10000,"empty":2407,"full":1416,"on_shipper":50,"on_consignee":0,"shortage":0,"acc_shortage":0,"booking":34,"acc_booking":6273,"fulfillment":34,"acc_fulfillment":6273,"transfer_cost":0.0,"port_name":"Seattle","position":{"lat":47.608013,"lng":-122.335167},"status":"surplus"},{"frame_index":112,"name":"ports_16","capacity":10000,"empty":2557,"full":647,"on_shipper":68,"on_consignee":0,"shortage":0,"acc_shortage":0,"booking":54,"acc_booking":8975,"fulfillment":54,"acc_fulfillment":8975,"transfer_cost":0.0,"port_name":"Shanghai","position":{"lat":31.224361,"lng":121.46917},"status":"surplus"},{"frame_index":112,"name":"ports_17","capacity":10000,"empty":1972,"full":173,"on_shipper":29,"on_consignee":0,"shortage":0,"acc_shortage":0,"booking":20,"acc_booking":3613,"fulfillment":20,"acc_fulfillment":3613,"transfer_cost":0.0,"port_name":"Singapore","position":{"lat":1.29027,"lng":103.851959},"status":"surplus"},{"frame_index":112,"name":"ports_18","capacity":10000,"empty":827,"full":12,"on_shipper":12,"on_consignee":0,"shortage":0,"acc_shortage":0,"booking":8,"acc_booking":1364,"fulfillment":8,"acc_fulfillment":1364,"transfer_cost":0.0,"port_name":"Sydney","position":{"lat":-33.865143,"lng":151.2099},"status":"surplus"},{"frame_index":112,"name":"ports_19","capacity":10000,"empty":674,"full":383,"on_shipper":13,"on_consignee":0,"shortage":0,"acc_shortage":0,"booking":11,"acc_booking":1843,"fulfillment":11,"acc_fulfillment":1843,"transfer_cost":0.0,"port_name":"Vancouver","position":{"lat":49.246292,"lng":-123.116226},"status":"surplus"},{"frame_index":112,"name":"ports_20","capacity":10000,"empty":1907,"full":399,"on_shipper":44,"on_consignee":0,"shortage":0,"acc_shortage":0,"booking":34,"acc_booking":6138,"fulfillment":34,"acc_fulfillment":6138,"transfer_cost":0.0,"port_name":"Yantian","position":{"lat":26.8533,"lng":119.8575},"status":"surplus"},{"frame_index":112,"name":"ports_21","capacity":10000,"empty":3672,"full":17,"on_shipper":44,"on_consignee":0,"shortage":0,"acc_shortage":0,"booking":30,"acc_booking":5912,"fulfillment":30,"acc_fulfillment":5912,"transfer_cost":0.0,"port_name":"Yokohama","position":{"lat":35.443707,"lng":139.638031},"status":"surplus"}]