[{"frame_index":663,"name":"ports_0","capacity":10000,"empty":5746,"full":3208,"on_shipper":86,"on_consignee":0,"shortage":0,"acc_shortage":522,"booking":35,"acc_booking":85480,"fulfillment":35,"acc_fulfillment":84958,"transfer_cost":0.0,"port_name":"Bremerhaven","position":{"lat":53.549999,"lng":8.583333},"status":"surplus"},{"frame_index":663,"name":"ports_1","capacity":10000,"empty":115,"full":126,"on_shipper":5,"on_consignee":0,"shortage":0,"acc_shortage":0,"booking":3,"acc_booking":5678,"fulfillment":3,"acc_fulfillment":5678,"transfer_cost":0.0,"port_name":"Durban","position":{"lat":-29.8579,"lng":31.0292},"status":"surplus"},{"frame_index":663,"name":"ports_2","capacity":10000,"empty":470,"full":60,"on_shipper":5,"on_consignee":0,"shortage":0,"acc_shortage":298,"booking":3,"acc_booking":5658,"fulfillment":3,"acc_fulfillment":5360,"transfer_cost":0.0,"port_name":"Itagual","position":{"lat":-22.85222,"lng":-43.77528},"status":"surplus"},{"frame_index":663,"name":"ports_3","capacity":10000,"empty":3694,"full":202,"on_shipper":33,"on_consignee":0,"shortage":0,"acc_shortage":0,"booking":14,"acc_booking":32339,"fulfillment":14,"acc_fulfillment":32339,"transfer_cost":0.0,"port_name":"LeHavre","position":{"lat":49.490002,"lng":0.1},"status":"surplus"},{"frame_index":663,"name":"ports_4","capacity":10000,"empty":2186,"full":433,"on_shipper":19,"on_consignee":0,"shortage":0,"acc_shortage":150,"booking":12,"acc_booking":27060,"fulfillment":12,"acc_fulfillment":26910,"transfer_cost":0.0,"port_name":"Los Angeles","position":{"lat":34.052235,"lng":-118.243683},"status":"surplus"},{"frame_index":663,"name":"ports_5","capacity":10000,"empty":1697,"full":48,"on_shipper":22,"on_consignee":0,"shortage":0,"acc_shortage":123,"booking":11,"acc_booking":27128,"fulfillment":11,"acc_fulfillment":27005,"transfer_cost":0.0,"port_name":"Manzanillo","position":{"lat":19.11695,"lng":-104.34214},"status":"surplus"},{"frame_index":663,"name":"ports_6","capacity":10000,"empty":306,"full":251,"on_shipper":11,"on_consignee":0,"shortage":0,"acc_shortage":1336,"booking":4,"acc_booking":8328,"fulfillment":4,"acc_fulfillment":6992,"transfer_cost":0.0,"port_name":"Melbourne","position":{"lat":-37.840935,"lng":144.946457},"status":"surplus"},{"frame_index":663,"name":"ports_7","capacity":10000,"empty":710,"full":117,"on_shipper":9,"on_consignee":0,"shortage":0,"acc_shortage":0,"booking":4,"acc_booking":8334,"fulfillment":4,"acc_fulfillment":8334,"transfer_cost":0.0,"port_name":"Montreal","position":{"lat":45.516136,"lng":-73.65683},"status":"surplus"},{"frame_index":663,"name":"ports_8","capacity":10000,"empty":983,"full":1925,"on_shipper":14,"on_consignee":0,"shortage":0,"acc_shortage":0,"booking":7,"acc_booking":16293,"fulfillment":7,"acc_fulfillment":16293,"transfer_cost":0.0,"port_name":"New York","position":{"lat":40.73061,"lng":-73.935242},"status":"surplus"},{"frame_index":663,"name":"ports_9","capacity":10000,"empty":808,"full":221,"on_shipper":10,"on_consignee":0,"shortage":0,"acc_shortage":45,"booking":7,"acc_booking":16358,"fulfillment":7,"acc_fulfillment":16313,"transfer_cost":0.0,"port_name":"Oakland","position":{"lat":37.804363,"lng":-122.271111},"status":"surplus"},{"frame_index":663,"name":"ports_10","capacity":10000,"empty":951,"full":144,"on_shipper":9,"on_consignee":0,"shortage":0,"acc_shortage":314,"booking":3,"acc_booking":8353,"fulfillment":3,"acc_fulfillment":8039,"transfer_cost":0.0,"port_name":"Prince Rupert","position":{"lat":54.312519,"lng":-130.305405},"status":"surplus"},{"frame_index":663,"name":"ports_11","capacity":10000,"empty":3092,"full":755,"on_shipper":36,"on_consignee":184,"shortage":0,"acc_shortage":204,"booking":15,"acc_booking":32301,"fulfillment":15,"acc_fulfillment":32097,"transfer_cost":0.0,"port_name":"Pusan","position":{"lat":35.166668,"lng":129.066666},"status":"surplus"},{"frame_index":663,"name":"ports_12","capacity":10000,"empty":1909,"full":1984,"on_shipper":44,"on_consignee":320,"shortage":0,"acc_shortage":0,"booking":18,"acc_booking":43105,"fulfillment":18,"acc_fulfillment":43105,"transfer_cost":0.0,"port_name":"Qingdao","position":{"lat":36.066898,"lng":120.382698},"status":"surplus"},{"frame_index":663,"name":"ports_13","capacity":10000,"empty":597,"full":129,"on_shipper":6,"on_consignee":0,"shortage":0,"acc_shortage":325,"booking":3,"acc_booking":5655,"fulfillment":3,"acc_fulfillment":5330,"transfer_cost":0.0,"port_name":"San Antonio","position":{"lat":29.424349,"lng":-98.491142},"status":"surplus"},{"frame_index":663,"name":"ports_14","capacity":10000,"empty":565,"full":199,"on_shipper":7,"on_consignee":0,"shortage":0,"acc_shortage":762,"booking":3,"acc_booking":5704,"fulfillment":3,"acc_fulfillment":4942,"transfer_cost":0.0,"port_name":"Santos","position":{"lat":-23.96083,"lng":-46.33361},"status":"surplus"},{"frame_index":663,"name":"ports_15","capacity":10000,"empty":1951,"full":1959,"on_shipper":46,"on_consignee":0,"shortage":0,"acc_shortage":0,"booking":16,"acc_booking":37671,"fulfillment":16,"acc_fulfillment":37671,"transfer_cost":0.0,"port_name":"Seattle","position":{"lat":47.608013,"lng":-122.335167},"status":"surplus"},{"frame_index":663,"name":"ports_16","capacity":10000,"empty":1036,"full":963,"on_shipper":51,"on_consignee":0,"shortage":0,"acc_shortage":712,"booking":27,"acc_booking":53663,"fulfillment":27,"acc_fulfillment":52951,"transfer_cost":0.0,"port_name":"Shanghai","position":{"lat":31.224361,"lng":121.46917},"status":"surplus"},{"frame_index":663,"name":"ports_17","capacity":10000,"empty":309,"full":599,"on_shipper":17,"on_consignee":480,"shortage":0,"acc_shortage":283,"booking":10,"acc_booking":21721,"fulfillment":10,"acc_fulfillment":21438,"transfer_cost":0.0,"port_name":"Singapore","position":{"lat":1.29027,"lng":103.851959},"status":"surplus"},{"frame_index":663,"name":"ports_18","capacity":10000,"empty":0,"full":265,"on_shipper":0,"on_consignee":0,"shortage":4,"acc_shortage":1046,"booking":4,"acc_booking":8298,"fulfillment":0,"acc_fulfillment":7252,"transfer_cost":0.0,"port_name":"Sydney","position":{"lat":-33.865143,"lng":151.2099},"status":"balance"},{"frame_index":663,"name":"ports_19","capacity":10000,"empty":563,"full":699,"on_shipper":10,"on_consignee":62,"shortage":0,"acc_shortage":0,"booking":5,"acc_booking":11060,"fulfillment":5,"acc_fulfillment":11060,"transfer_cost":0.0,"port_name":"Vancouver","position":{"lat":49.246292,"lng":-123.116226},"status":"surplus"},{"frame_index":663,"name":"ports_20","capacity":10000,"empty":716,"full":469,"on_shipper":31,"on_consignee":337,"shortage":0,"acc_shortage":395,"booking":15,"acc_booking":37426,"fulfillment":15,"acc_fulfillment":37031,"transfer_cost":72.0,"port_name":"Yantian","position":{"lat":26.8533,"lng":119.8575},"status":"surplus"},{"frame_index":663,"name":"ports_21","capacity":10000,"empty":0,"full":2432,"on_shipper":0,"on_consignee":0,"shortage":7,"acc_shortage":4051,"booking":7,"acc_booking":35764,"fulfillment":0,"acc_fulfillment":31713,"transfer_cost":0.0,"port_name":"Yokohama","position":{"lat":35.443707,"lng":139.638031},"status":"balance"}]