[{"frame_index":34,"name":"ports_0","capacity":10000,"empty":13037,"full":1744,"on_shipper":262,"on_consignee":0,"shortage":0,"acc_shortage":0,"booking":143,"acc_booking":2963,"fulfillment":143,"acc_fulfillment":2963,"transfer_cost":0.0,"port_name":"Bremerhaven","position":{"lat":53.549999,"lng":8.583333},"status":"surplus"},{"frame_index":34,"name":"ports_1","capacity":10000,"empty":808,"full":114,"on_shipper":14,"on_consignee":0,"shortage":0,"acc_shortage":0,"booking":9,"acc_booking":203,"fulfillment":9,"acc_fulfillment":203,"transfer_cost":0.0,"port_name":"Durban","position":{"lat":-29.8579,"lng":31.0292},"status":"surplus"},{"frame_index":34,"name":"ports_2","capacity":10000,"empty":831,"full":5,"on_shipper":15,"on_consignee":0,"shortage":0,"acc_shortage":0,"booking":9,"acc_booking":201,"fulfillment":9,"acc_fulfillment":201,"transfer_cost":0.0,"port_name":"Itagual","position":{"lat":-22.85222,"lng":-43.77528},"status":"surplus"},{"frame_index":34,"name":"ports_3","capacity":10000,"empty":4198,"full":343,"on_shipper":68,"on_consignee":0,"shortage":0,"acc_shortage":0,"booking":50,"acc_booking":1138,"fulfillment":50,"acc_fulfillment":1138,"transfer_cost":0.0,"port_name":"LeHavre","position":{"lat":49.490002,"lng":0.1},"status":"surplus"},{"frame_index":34,"name":"ports_4","capacity":10000,"empty":4050,"full":436,"on_shipper":49,"on_consignee":0,"shortage":0,"acc_shortage":0,"booking":42,"acc_booking":950,"fulfillment":42,"acc_fulfillment":950,"transfer_cost":0.0,"port_name":"Los Angeles","position":{"lat":34.052235,"lng":-118.243683},"status":"surplus"},{"frame_index":34,"name":"ports_5","capacity":10000,"empty":4041,"full":447,"on_shipper":68,"on_consignee":0,"shortage":0,"acc_shortage":0,"booking":45,"acc_booking":959,"fulfillment":45,"acc_fulfillment":959,"transfer_cost":0.0,"port_name":"Manzanillo","position":{"lat":19.11695,"lng":-104.34214},"status":"surplus"},{"frame_index":34,"name":"ports_6","capacity":10000,"empty":1205,"full":164,"on_shipper":17,"on_consignee":0,"shortage":0,"acc_shortage":0,"booking":13,"acc_booking":295,"fulfillment":13,"acc_fulfillment":295,"transfer_cost":0.0,"port_name":"Melbourne","position":{"lat":-37.840935,"lng":144.946457},"status":"surplus"},{"frame_index":34,"name":"ports_7","capacity":10000,"empty":1733,"full":72,"on_shipper":25,"on_consignee":0,"shortage":0,"acc_shortage":0,"booking":13,"acc_booking":293,"fulfillment":13,"acc_fulfillment":293,"transfer_cost":0.0,"port_name":"Montreal","position":{"lat":45.516136,"lng":-73.65683},"status":"surplus"},{"frame_index":34,"name":"ports_8","capacity":10000,"empty":2423,"full":538,"on_shipper":39,"on_consignee":0,"shortage":0,"acc_shortage":0,"booking":25,"acc_booking":577,"fulfillment":25,"acc_fulfillment":577,"transfer_cost":0.0,"port_name":"New York","position":{"lat":40.73061,"lng":-73.935242},"status":"surplus"},{"frame_index":34,"name":"ports_9","capacity":10000,"empty":2435,"full":532,"on_shipper":33,"on_consignee":0,"shortage":0,"acc_shortage":0,"booking":22,"acc_booking":565,"fulfillment":22,"acc_fulfillment":565,"transfer_cost":0.0,"port_name":"Oakland","position":{"lat":37.804363,"lng":-122.271111},"status":"surplus"},{"frame_index":34,"name":"ports_10","capacity":10000,"empty":1190,"full":291,"on_shipper":19,"on_consignee":0,"shortage":0,"acc_shortage":0,"booking":15,"acc_booking":310,"fulfillment":15,"acc_fulfillment":310,"transfer_cost":0.0,"port_name":"Prince Rupert","position":{"lat":54.312519,"lng":-130.305405},"status":"surplus"},{"frame_index":34,"name":"ports_11","capacity":10000,"empty":4880,"full":226,"on_shipper":76,"on_consignee":17,"shortage":0,"acc_shortage":0,"booking":48,"acc_booking":1124,"fulfillment":48,"acc_fulfillment":1124,"transfer_cost":0.0,"port_name":"Pusan","position":{"lat":35.166668,"lng":129.066666},"status":"surplus"},{"frame_index":34,"name":"ports_12","capacity":10000,"empty":6494,"full":1066,"on_shipper":89,"on_consignee":0,"shortage":0,"acc_shortage":0,"booking":60,"acc_booking":1506,"fulfillment":60,"acc_fulfillment":1506,"transfer_cost":0.0,"port_name":"Qingdao","position":{"lat":36.066898,"lng":120.382698},"status":"surplus"},{"frame_index":34,"name":"ports_13","capacity":10000,"empty":797,"full":10,"on_shipper":13,"on_consignee":0,"shortage":0,"acc_shortage":0,"booking":9,"acc_booking":203,"fulfillment":9,"acc_fulfillment":203,"transfer_cost":0.0,"port_name":"San Antonio","position":{"lat":29.424349,"lng":-98.491142},"status":"surplus"},{"frame_index":34,"name":"ports_14","capacity":10000,"empty":799,"full":187,"on_shipper":14,"on_consignee":0,"shortage":0,"acc_shortage":0,"booking":8,"acc_booking":201,"fulfillment":8,"acc_fulfillment":201,"transfer_cost":0.0,"port_name":"Santos","position":{"lat":-23.96083,"lng":-46.33361},"status":"surplus"},{"frame_index":34,"name":"ports_15","capacity":10000,"empty":5676,"full":770,"on_shipper":79,"on_consignee":14,"shortage":0,"acc_shortage":0,"booking":56,"acc_booking":1324,"fulfillment":56,"acc_fulfillment":1324,"transfer_cost":0.0,"port_name":"Seattle","position":{"lat":47.608013,"lng":-122.335167},"status":"surplus"},{"frame_index":34,"name":"ports_16","capacity":10000,"empty":8128,"full":985,"on_shipper":132,"on_consignee":0,"shortage":0,"acc_shortage":0,"booking":97,"acc_booking":1906,"fulfillment":97,"acc_fulfillment":1906,"transfer_cost":0.0,"port_name":"Shanghai","position":{"lat":31.224361,"lng":121.46917},"status":"surplus"},{"frame_index":34,"name":"ports_17","capacity":10000,"empty":3244,"full":417,"on_shipper":39,"on_consignee":4,"shortage":0,"acc_shortage":0,"booking":34,"acc_booking":767,"fulfillment":34,"acc_fulfillment":767,"transfer_cost":0.0,"port_name":"Singapore","position":{"lat":1.29027,"lng":103.851959},"status":"surplus"},{"frame_index":34,"name":"ports_18","capacity":10000,"empty":1206,"full":104,"on_shipper":17,"on_consignee":0,"shortage":0,"acc_shortage":0,"booking":13,"acc_booking":294,"fulfillment":13,"acc_fulfillment":294,"transfer_cost":0.0,"port_name":"Sydney","position":{"lat":-33.865143,"lng":151.2099},"status":"surplus"},{"frame_index":34,"name":"ports_19","capacity":10000,"empty":1632,"full":43,"on_shipper":23,"on_consignee":0,"shortage":0,"acc_shortage":0,"booking":16,"acc_booking":387,"fulfillment":16,"acc_fulfillment":387,"transfer_cost":0.0,"port_name":"Vancouver","position":{"lat":49.246292,"lng":-123.116226},"status":"surplus"},{"frame_index":34,"name":"ports_20","capacity":10000,"empty":5683,"full":780,"on_shipper":92,"on_consignee":0,"shortage":0,"acc_shortage":0,"booking":59,"acc_booking":1322,"fulfillment":59,"acc_fulfillment":1322,"transfer_cost":0.0,"port_name":"Yantian","position":{"lat":26.8533,"lng":119.8575},"status":"surplus"},{"frame_index":34,"name":"ports_21","capacity":10000,"empty":6860,"full":1072,"on_shipper":68,"on_consignee":0,"shortage":0,"acc_shortage":0,"booking":54,"acc_booking":1140,"fulfillment":54,"acc_fulfillment":1140,"transfer_cost":0.0,"port_name":"Yokohama","position":{"lat":35.443707,"lng":139.638031},"status":"surplus"}]