[{"frame_index":831,"name":"ports_0","capacity":10000,"empty":2168,"full":6384,"on_shipper":323,"on_consignee":0,"shortage":0,"acc_shortage":522,"booking":199,"acc_booking":106061,"fulfillment":199,"acc_fulfillment":105539,"transfer_cost":0.0,"port_name":"Bremerhaven","position":{"lat":53.549999,"lng":8.583333},"status":"surplus"},{"frame_index":831,"name":"ports_1","capacity":10000,"empty":267,"full":126,"on_shipper":20,"on_consignee":0,"shortage":0,"acc_shortage":10,"booking":13,"acc_booking":7050,"fulfillment":13,"acc_fulfillment":7040,"transfer_cost":0.0,"port_name":"Durban","position":{"lat":-29.8579,"lng":31.0292},"status":"surplus"},{"frame_index":831,"name":"ports_2","capacity":10000,"empty":163,"full":408,"on_shipper":17,"on_consignee":0,"shortage":0,"acc_shortage":298,"booking":13,"acc_booking":7020,"fulfillment":13,"acc_fulfillment":6722,"transfer_cost":0.0,"port_name":"Itagual","position":{"lat":-22.85222,"lng":-43.77528},"status":"surplus"},{"frame_index":831,"name":"ports_3","capacity":10000,"empty":4346,"full":785,"on_shipper":143,"on_consignee":0,"shortage":0,"acc_shortage":0,"booking":81,"acc_booking":40138,"fulfillment":81,"acc_fulfillment":40138,"transfer_cost":0.0,"port_name":"LeHavre","position":{"lat":49.490002,"lng":0.1},"status":"surplus"},{"frame_index":831,"name":"ports_4","capacity":10000,"empty":1062,"full":1024,"on_shipper":120,"on_consignee":0,"shortage":0,"acc_shortage":290,"booking":68,"acc_booking":33603,"fulfillment":68,"acc_fulfillment":33313,"transfer_cost":0.0,"port_name":"Los Angeles","position":{"lat":34.052235,"lng":-118.243683},"status":"surplus"},{"frame_index":831,"name":"ports_5","capacity":10000,"empty":2088,"full":1034,"on_shipper":127,"on_consignee":0,"shortage":0,"acc_shortage":123,"booking":68,"acc_booking":33748,"fulfillment":68,"acc_fulfillment":33625,"transfer_cost":0.0,"port_name":"Manzanillo","position":{"lat":19.11695,"lng":-104.34214},"status":"surplus"},{"frame_index":831,"name":"ports_6","capacity":10000,"empty":136,"full":306,"on_shipper":28,"on_consignee":0,"shortage":0,"acc_shortage":1654,"booking":20,"acc_booking":10347,"fulfillment":20,"acc_fulfillment":8693,"transfer_cost":0.0,"port_name":"Melbourne","position":{"lat":-37.840935,"lng":144.946457},"status":"balance"},{"frame_index":831,"name":"ports_7","capacity":10000,"empty":948,"full":79,"on_shipper":20,"on_consignee":0,"shortage":0,"acc_shortage":0,"booking":20,"acc_booking":10360,"fulfillment":20,"acc_fulfillment":10360,"transfer_cost":0.0,"port_name":"Montreal","position":{"lat":45.516136,"lng":-73.65683},"status":"surplus"},{"frame_index":831,"name":"ports_8","capacity":10000,"empty":3405,"full":354,"on_shipper":39,"on_consignee":0,"shortage":0,"acc_shortage":136,"booking":39,"acc_booking":20226,"fulfillment":39,"acc_fulfillment":20090,"transfer_cost":0.0,"port_name":"New York","position":{"lat":40.73061,"lng":-73.935242},"status":"surplus"},{"frame_index":831,"name":"ports_9","capacity":10000,"empty":749,"full":858,"on_shipper":67,"on_consignee":0,"shortage":0,"acc_shortage":45,"booking":40,"acc_booking":20272,"fulfillment":40,"acc_fulfillment":20227,"transfer_cost":0.0,"port_name":"Oakland","position":{"lat":37.804363,"lng":-122.271111},"status":"surplus"},{"frame_index":831,"name":"ports_10","capacity":10000,"empty":1002,"full":468,"on_shipper":30,"on_consignee":0,"shortage":0,"acc_shortage":314,"booking":23,"acc_booking":10373,"fulfillment":23,"acc_fulfillment":10059,"transfer_cost":0.0,"port_name":"Prince Rupert","position":{"lat":54.312519,"lng":-130.305405},"status":"surplus"},{"frame_index":831,"name":"ports_11","capacity":10000,"empty":2640,"full":868,"on_shipper":133,"on_consignee":0,"shortage":0,"acc_shortage":204,"booking":78,"acc_booking":40110,"fulfillment":78,"acc_fulfillment":39906,"transfer_cost":0.0,"port_name":"Pusan","position":{"lat":35.166668,"lng":129.066666},"status":"surplus"},{"frame_index":831,"name":"ports_12","capacity":10000,"empty":3690,"full":1950,"on_shipper":212,"on_consignee":99,"shortage":0,"acc_shortage":0,"booking":115,"acc_booking":53560,"fulfillment":115,"acc_fulfillment":53560,"transfer_cost":0.0,"port_name":"Qingdao","position":{"lat":36.066898,"lng":120.382698},"status":"surplus"},{"frame_index":831,"name":"ports_13","capacity":10000,"empty":589,"full":129,"on_shipper":22,"on_consignee":0,"shortage":0,"acc_shortage":449,"booking":15,"acc_booking":7032,"fulfillment":15,"acc_fulfillment":6583,"transfer_cost":0.0,"port_name":"San Antonio","position":{"lat":29.424349,"lng":-98.491142},"status":"surplus"},{"frame_index":831,"name":"ports_14","capacity":10000,"empty":585,"full":8,"on_shipper":24,"on_consignee":0,"shortage":0,"acc_shortage":819,"booking":16,"acc_booking":7065,"fulfillment":16,"acc_fulfillment":6246,"transfer_cost":0.0,"port_name":"Santos","position":{"lat":-23.96083,"lng":-46.33361},"status":"surplus"},{"frame_index":831,"name":"ports_15","capacity":10000,"empty":1258,"full":1798,"on_shipper":114,"on_consignee":0,"shortage":0,"acc_shortage":0,"booking":91,"acc_booking":46822,"fulfillment":91,"acc_fulfillment":46822,"transfer_cost":0.0,"port_name":"Seattle","position":{"lat":47.608013,"lng":-122.335167},"status":"surplus"},{"frame_index":831,"name":"ports_16","capacity":10000,"empty":2296,"full":1984,"on_shipper":189,"on_consignee":0,"shortage":0,"acc_shortage":760,"booking":122,"acc_booking":66582,"fulfillment":122,"acc_fulfillment":65822,"transfer_cost":0.0,"port_name":"Shanghai","position":{"lat":31.224361,"lng":121.46917},"status":"surplus"},{"frame_index":831,"name":"ports_17","capacity":10000,"empty":365,"full":653,"on_shipper":76,"on_consignee":0,"shortage":0,"acc_shortage":283,"booking":55,"acc_booking":26963,"fulfillment":55,"acc_fulfillment":26680,"transfer_cost":0.0,"port_name":"Singapore","position":{"lat":1.29027,"lng":103.851959},"status":"surplus"},{"frame_index":831,"name":"ports_18","capacity":10000,"empty":919,"full":295,"on_shipper":36,"on_consignee":0,"shortage":0,"acc_shortage":1374,"booking":23,"acc_booking":10363,"fulfillment":23,"acc_fulfillment":8989,"transfer_cost":0.0,"port_name":"Sydney","position":{"lat":-33.865143,"lng":151.2099},"status":"surplus"},{"frame_index":831,"name":"ports_19","capacity":10000,"empty":1347,"full":290,"on_shipper":47,"on_consignee":0,"shortage":0,"acc_shortage":0,"booking":29,"acc_booking":13728,"fulfillment":29,"acc_fulfillment":13728,"transfer_cost":0.0,"port_name":"Vancouver","position":{"lat":49.246292,"lng":-123.116226},"status":"surplus"},{"frame_index":831,"name":"ports_20","capacity":10000,"empty":914,"full":1244,"on_shipper":163,"on_consignee":0,"shortage":0,"acc_shortage":942,"booking":103,"acc_booking":46547,"fulfillment":103,"acc_fulfillment":45605,"transfer_cost":0.0,"port_name":"Yantian","position":{"lat":26.8533,"lng":119.8575},"status":"surplus"},{"frame_index":831,"name":"ports_21","capacity":10000,"empty":1273,"full":476,"on_shipper":148,"on_consignee":0,"shortage":0,"acc_shortage":6236,"booking":96,"acc_booking":44316,"fulfillment":96,"acc_fulfillment":38080,"transfer_cost":0.0,"port_name":"Yokohama","position":{"lat":35.443707,"lng":139.638031},"status":"surplus"}]