[{"tick":448,"src_port_idx":0,"dest_port_idx":3,"quantity":4},{"tick":448,"src_port_idx":0,"dest_port_idx":7,"quantity":2},{"tick":448,"src_port_idx":0,"dest_port_idx":8,"quantity":10},{"tick":448,"src_port_idx":0,"dest_port_idx":11,"quantity":2},{"tick":448,"src_port_idx":0,"dest_port_idx":12,"quantity":1},{"tick":448,"src_port_idx":0,"dest_port_idx":16,"quantity":1},{"tick":448,"src_port_idx":1,"dest_port_idx":12,"quantity":1},{"tick":448,"src_port_idx":1,"dest_port_idx":16,"quantity":1},{"tick":448,"src_port_idx":2,"dest_port_idx":12,"quantity":1},{"tick":448,"src_port_idx":2,"dest_port_idx":14,"quantity":1},{"tick":448,"src_port_idx":3,"dest_port_idx":0,"quantity":2},{"tick":448,"src_port_idx":3,"dest_port_idx":7,"quantity":1},{"tick":448,"src_port_idx":3,"dest_port_idx":8,"quantity":2},{"tick":448,"src_port_idx":3,"dest_port_idx":11,"quantity":1},{"tick":448,"src_port_idx":3,"dest_port_idx":12,"quantity":1},{"tick":448,"src_port_idx":4,"dest_port_idx":9,"quantity":2},{"tick":448,"src_port_idx":4,"dest_port_idx":10,"quantity":1},{"tick":448,"src_port_idx":4,"dest_port_idx":12,"quantity":1},{"tick":448,"src_port_idx":4,"dest_port_idx":15,"quantity":2},{"tick":448,"src_port_idx":5,"dest_port_idx":5,"quantity":1},{"tick":448,"src_port_idx":5,"dest_port_idx":11,"quantity":1},{"tick":448,"src_port_idx":5,"dest_port_idx":12,"quantity":1},{"tick":448,"src_port_idx":5,"dest_port_idx":13,"quantity":1},{"tick":448,"src_port_idx":5,"dest_port_idx":16,"quantity":1},{"tick":448,"src_port_idx":5,"dest_port_idx":20,"quantity":1},{"tick":448,"src_port_idx":6,"dest_port_idx":17,"quantity":1},{"tick":448,"src_port_idx":6,"dest_port_idx":18,"quantity":1},{"tick":448,"src_port_idx":7,"dest_port_idx":0,"quantity":2},{"tick":448,"src_port_idx":8,"dest_port_idx":0,"quantity":3},{"tick":448,"src_port_idx":8,"dest_port_idx":3,"quantity":1},{"tick":448,"src_port_idx":9,"dest_port_idx":4,"quantity":2},{"tick":448,"src_port_idx":9,"dest_port_idx":10,"quantity":1},{"tick":448,"src_port_idx":9,"dest_port_idx":12,"quantity":1},{"tick":448,"src_port_idx":10,"dest_port_idx":4,"quantity":1},{"tick":448,"src_port_idx":10,"dest_port_idx":9,"quantity":1},{"tick":448,"src_port_idx":11,"dest_port_idx":0,"quantity":2},{"tick":448,"src_port_idx":11,"dest_port_idx":3,"quantity":1},{"tick":448,"src_port_idx":11,"dest_port_idx":5,"quantity":1},{"tick":448,"src_port_idx":11,"dest_port_idx":12,"quantity":1},{"tick":448,"src_port_idx":11,"dest_port_idx":13,"quantity":1},{"tick":448,"src_port_idx":11,"dest_port_idx":15,"quantity":1},{"tick":448,"src_port_idx":12,"dest_port_idx":0,"quantity":2},{"tick":448,"src_port_idx":12,"dest_port_idx":1,"quantity":1},{"tick":448,"src_port_idx":12,"dest_port_idx":2,"quantity":1},{"tick":448,"src_port_idx":12,"dest_port_idx":3,"quantity":1},{"tick":448,"src_port_idx":12,"dest_port_idx":4,"quantity":2},{"tick":448,"src_port_idx":12,"dest_port_idx":5,"quantity":1},{"tick":448,"src_port_idx":12,"dest_port_idx":9,"quantity":2},{"tick":448,"src_port_idx":12,"dest_port_idx":10,"quantity":1},{"tick":448,"src_port_idx":13,"dest_port_idx":5,"quantity":1},{"tick":448,"src_port_idx":13,"dest_port_idx":11,"quantity":1},{"tick":448,"src_port_idx":14,"dest_port_idx":2,"quantity":1},{"tick":448,"src_port_idx":15,"dest_port_idx":4,"quantity":3},{"tick":448,"src_port_idx":15,"dest_port_idx":11,"quantity":2},{"tick":448,"src_port_idx":15,"dest_port_idx":12,"quantity":1},{"tick":448,"src_port_idx":15,"dest_port_idx":16,"quantity":2},{"tick":448,"src_port_idx":15,"dest_port_idx":17,"quantity":1},{"tick":448,"src_port_idx":16,"dest_port_idx":0,"quantity":3},{"tick":448,"src_port_idx":16,"dest_port_idx":1,"quantity":1},{"tick":448,"src_port_idx":16,"dest_port_idx":2,"quantity":1},{"tick":448,"src_port_idx":16,"dest_port_idx":3,"quantity":1},{"tick":448,"src_port_idx":16,"dest_port_idx":4,"quantity":2},{"tick":448,"src_port_idx":16,"dest_port_idx":5,"quantity":1},{"tick":448,"src_port_idx":16,"dest_port_idx":9,"quantity":2},{"tick":448,"src_port_idx":17,"dest_port_idx":0,"quantity":1},{"tick":448,"src_port_idx":17,"dest_port_idx":1,"quantity":1},{"tick":448,"src_port_idx":17,"dest_port_idx":2,"quantity":1},{"tick":448,"src_port_idx":17,"dest_port_idx":3,"quantity":1},{"tick":448,"src_port_idx":17,"dest_port_idx":6,"quantity":1},{"tick":448,"src_port_idx":18,"dest_port_idx":6,"quantity":1},{"tick":448,"src_port_idx":18,"dest_port_idx":17,"quantity":1},{"tick":448,"src_port_idx":19,"dest_port_idx":11,"quantity":1},{"tick":448,"src_port_idx":19,"dest_port_idx":12,"quantity":1},{"tick":448,"src_port_idx":19,"dest_port_idx":15,"quantity":1},{"tick":448,"src_port_idx":20,"dest_port_idx":0,"quantity":2},{"tick":448,"src_port_idx":20,"dest_port_idx":1,"quantity":1},{"tick":448,"src_port_idx":20,"dest_port_idx":2,"quantity":1},{"tick":448,"src_port_idx":20,"dest_port_idx":3,"quantity":1},{"tick":448,"src_port_idx":20,"dest_port_idx":5,"quantity":1}]